odoo/addons/l10n_es_ticketbai_api/README.rst
odoo/addons/l10n_es_ticketbai_api/__init__.py
odoo/addons/l10n_es_ticketbai_api/__manifest__.py
odoo/addons/l10n_es_ticketbai_api/data/tax_agency_data.xml
odoo/addons/l10n_es_ticketbai_api/data/ticketbai_invoice.xml
odoo/addons/l10n_es_ticketbai_api/demo/res_partner_demo.xml
odoo/addons/l10n_es_ticketbai_api/i18n/es.po
odoo/addons/l10n_es_ticketbai_api/i18n/eu.po
odoo/addons/l10n_es_ticketbai_api/i18n/l10n_es_ticketbai_api.pot
odoo/addons/l10n_es_ticketbai_api/migrations/13.0.1.5.0/noupdate_changes.xml
odoo/addons/l10n_es_ticketbai_api/migrations/13.0.1.5.0/post-migration.py
odoo/addons/l10n_es_ticketbai_api/migrations/13.0.1.5.7/post-migrate.py
odoo/addons/l10n_es_ticketbai_api/models/__init__.py
odoo/addons/l10n_es_ticketbai_api/models/res_company.py
odoo/addons/l10n_es_ticketbai_api/models/res_config_settings.py
odoo/addons/l10n_es_ticketbai_api/models/res_country.py
odoo/addons/l10n_es_ticketbai_api/models/res_partner.py
odoo/addons/l10n_es_ticketbai_api/models/ticketbai_certificate.py
odoo/addons/l10n_es_ticketbai_api/models/ticketbai_installation.py
odoo/addons/l10n_es_ticketbai_api/models/ticketbai_invoice.py
odoo/addons/l10n_es_ticketbai_api/models/ticketbai_invoice_customer.py
odoo/addons/l10n_es_ticketbai_api/models/ticketbai_invoice_line.py
odoo/addons/l10n_es_ticketbai_api/models/ticketbai_invoice_tax.py
odoo/addons/l10n_es_ticketbai_api/models/ticketbai_response.py
odoo/addons/l10n_es_ticketbai_api/models/ticketbai_tax_agency.py
odoo/addons/l10n_es_ticketbai_api/security/ir.model.access.csv
odoo/addons/l10n_es_ticketbai_api/security/l10n_es_ticketbai_security.xml
odoo/addons/l10n_es_ticketbai_api/static/description/icon.png
odoo/addons/l10n_es_ticketbai_api/static/src/img/binovo_logo.jpg
odoo/addons/l10n_es_ticketbai_api/static/src/img/derbi.png
odoo/addons/l10n_es_ticketbai_api/static/src/img/oca_logo.png
odoo/addons/l10n_es_ticketbai_api/static/src/img/peugeot.png
odoo13_addon_l10n_es_ticketbai_api-13.0.1.5.8.dist-info/METADATA
odoo13_addon_l10n_es_ticketbai_api-13.0.1.5.8.dist-info/WHEEL
odoo13_addon_l10n_es_ticketbai_api-13.0.1.5.8.dist-info/top_level.txt
odoo13_addon_l10n_es_ticketbai_api-13.0.1.5.8.dist-info/RECORD
